docdundee/__init__.py
docdundee/docparser.py
docdundee/interfaces.py
docdundee-0.0.6.dist-info/METADATA
docdundee-0.0.6.dist-info/WHEEL
docdundee-0.0.6.dist-info/top_level.txt
docdundee-0.0.6.dist-info/RECORD
