Metadata-Version: 2.1
Name: docdundee
Version: 0.0.6
Summary: Parse docstrings into json
Home-page: https://github.com/synw/docdundee/package/pdocdundee
Download-URL: https://github.com/synw/docdundee/releases/tag/0.0.6
Author: synw
Author-email: synwe@yahoo.com
Keywords: documentation,docstrings
Classifier: Development Status :: 3 - Alpha
Classifier: Intended Audience :: Developers
Classifier: License :: OSI Approved :: MIT License
Classifier: Programming Language :: Python :: 3.10
Requires-Dist: docutils
Requires-Dist: docstring-parser
